fibu.py
fibu_slechler-1.0.0.dist-info/DESCRIPTION.rst
fibu_slechler-1.0.0.dist-info/METADATA
fibu_slechler-1.0.0.dist-info/RECORD
fibu_slechler-1.0.0.dist-info/WHEEL
fibu_slechler-1.0.0.dist-info/metadata.json
fibu_slechler-1.0.0.dist-info/top_level.txt
