Metadata-Version: 2.0
Name: fibu-slechler
Version: 1.0.0
Summary: fibutest
Home-page: http://www.headfirstlabs.com
Author: slechler
Author-email: lechler@gmx.com
License: UNKNOWN
Platform: UNKNOWN
